setup.py
D8gerConcurrent.egg-info/PKG-INFO
D8gerConcurrent.egg-info/SOURCES.txt
D8gerConcurrent.egg-info/dependency_links.txt
D8gerConcurrent.egg-info/entry_points.txt
D8gerConcurrent.egg-info/requires.txt
D8gerConcurrent.egg-info/top_level.txt
d8ger/CufflinksDemo.py
d8ger/DubleArrayTireTest.py
d8ger/__init__.py
d8ger/d8ger_check_jd.py
d8ger/d8ger_jd_post.py
d8ger/easy_test.py
d8ger/excel.py
d8ger/fk_app_config.py
d8ger/login_cookie.py
d8ger/oh_my_d8ger.py
d8ger/vesta.py